demopy/__init__.py
demopy/_rust.cpython-312-darwin.so
demopy_gb_jj-0.6.1.dist-info/METADATA
demopy_gb_jj-0.6.1.dist-info/WHEEL
demopy_gb_jj-0.6.1.dist-info/licenses/LICENSE
demopy_gb_jj-0.6.1.dist-info/RECORD
