Metadata-Version: 2.4
Name: demopy_gb_jj
Version: 0.6.1
Classifier: Development Status :: 4 - Beta
Classifier: Intended Audience :: Developers
Classifier: License :: OSI Approved :: MIT License
Classifier: Programming Language :: Python :: 3
Classifier: Programming Language :: Python :: 3.8
Classifier: Programming Language :: Python :: 3.9
Classifier: Programming Language :: Python :: 3.10
Classifier: Programming Language :: Python :: 3.11
Classifier: Programming Language :: Python :: 3.12
Classifier: Programming Language :: Python :: 3.13
Classifier: Programming Language :: Rust
License-File: LICENSE
Summary: A demo PyPI package with Rust extensions
Keywords: rust,python,pyo3,extension
Author-email: jj-devhub <Jaid.jashim@infinitibit.com>
License: MIT
Requires-Python: >=3.8
Project-URL: Homepage, https://github.com/jj-devhub/demopy
Project-URL: Repository, https://github.com/jj-devhub/demopy
Project-URL: Issues, https://github.com/jj-devhub/demopy/issues
